MANIFEST.in
README.md
setup.py
ipython2cwl/__init__.py
ipython2cwl/cwltoolextractor.py
ipython2cwl/iotypes.py
ipython2cwl/repo2cwl.py
ipython2cwl/requirements_manager.py
ipython2cwl/templates/template.dockerfile
ipython2cwl/templates/template.setup
ipython2cwlmosorio.egg-info/PKG-INFO
ipython2cwlmosorio.egg-info/SOURCES.txt
ipython2cwlmosorio.egg-info/dependency_links.txt
ipython2cwlmosorio.egg-info/entry_points.txt
ipython2cwlmosorio.egg-info/requires.txt
ipython2cwlmosorio.egg-info/top_level.txt